odoo/addons/survey_crm_sale_generation/README.rst
odoo/addons/survey_crm_sale_generation/__init__.py
odoo/addons/survey_crm_sale_generation/__manifest__.py
odoo/addons/survey_crm_sale_generation/demo/survey_sale_demo.xml
odoo/addons/survey_crm_sale_generation/i18n/es.po
odoo/addons/survey_crm_sale_generation/i18n/it.po
odoo/addons/survey_crm_sale_generation/i18n/survey_crm_sale_generation.pot
odoo/addons/survey_crm_sale_generation/models/__init__.py
odoo/addons/survey_crm_sale_generation/models/sale_order.py
odoo/addons/survey_crm_sale_generation/models/survey_user_input.py
odoo/addons/survey_crm_sale_generation/readme/CONFIGURE.md
odoo/addons/survey_crm_sale_generation/readme/CONTRIBUTORS.md
odoo/addons/survey_crm_sale_generation/readme/DESCRIPTION.md
odoo/addons/survey_crm_sale_generation/readme/USAGE.md
odoo/addons/survey_crm_sale_generation/static/description/icon.png
odoo/addons/survey_crm_sale_generation/static/description/index.html
odoo/addons/survey_crm_sale_generation/tests/__init__.py
odoo/addons/survey_crm_sale_generation/tests/test_survey_crm_sale_generation.py
odoo_addon_survey_crm_sale_generation-17.0.1.0.0.2.dist-info/METADATA
odoo_addon_survey_crm_sale_generation-17.0.1.0.0.2.dist-info/WHEEL
odoo_addon_survey_crm_sale_generation-17.0.1.0.0.2.dist-info/top_level.txt
odoo_addon_survey_crm_sale_generation-17.0.1.0.0.2.dist-info/RECORD
